LscEncryption/BinaryRecursiveMergeEncryption.py
LscEncryption/ShuffleEncryption.py
LscEncryption/__init__.py
lscencryption-0.0.2.dist-info/licenses/LICENSE
lscencryption-0.0.2.dist-info/METADATA
lscencryption-0.0.2.dist-info/WHEEL
lscencryption-0.0.2.dist-info/top_level.txt
lscencryption-0.0.2.dist-info/RECORD
