Metadata-Version: 2.4
Name: LscEncryption
Version: 0.0.2
Summary: 加密方法（整合）
Author-email: Linsc <1344343923@qq.com>
Classifier: Programming Language :: Python :: 3
Classifier: License :: OSI Approved :: MIT License
Classifier: Operating System :: OS Independent
Requires-Python: >=3.7
License-File: LICENSE
Dynamic: license-file
